{
    "properties": {
        "name": {
            "type": "text",
            "fields": {
                "keyword": {
                    "type": "keyword",
                    "normalizer": "lowercase_normalizer"
                },
                "english": {
                    "type": "text",
                    "analyzer": "english_analyzer"
                }
            }
        },
        "preferred_name": {
            "type": "text",
            "fields": {
                "keyword": {
                    "type": "keyword",
                    "normalizer": "lowercase_normalizer"
                },
                "english": {
                    "type": "text",
                    "analyzer": "english_analyzer"
                }
            }
        },
        "wikidata_preferred_name": {
            "type": "text",
            "fields": {
                "keyword": {
                    "type": "keyword",
                    "normalizer": "lowercase_normalizer"
                },
                "english": {
                    "type": "text",
                    "analyzer": "english_analyzer"
                }
            }
        },
        "variants": {
            "type": "text",
            "fields": {
                "keyword": {
                    "type": "keyword",
                    "normalizer": "lowercase_normalizer"
                },
                "english": {
                    "type": "text",
                    "analyzer": "english_analyzer"
                }
            }
        },
        "wikidata_description": {
            "type": "text",
            "analyzer": "english_analyzer"
        },
        "wikidata_id": {
            "type": "keyword",
            "normalizer": "lowercase_normalizer"
        },
        "stories": {
            "type": "text",
            "fields": {
                "keyword": {
                    "type": "keyword",
                    "normalizer": "lowercase_normalizer"
                },
                "english": {
                    "type": "text",
                    "analyzer": "english_analyzer"
                },
                "shingles": {
                    "type": "text",
                    "analyzer": "shingle_asciifolding_analyzer"
                }
            }
        },
        "story_ids": {
            "type": "keyword"
        }
    }
}
